googletranslate_neon_plugin/__init__.py
googletranslate_neon_plugin-0.1.1a0.dist-info/METADATA
googletranslate_neon_plugin-0.1.1a0.dist-info/WHEEL
googletranslate_neon_plugin-0.1.1a0.dist-info/entry_points.txt
googletranslate_neon_plugin-0.1.1a0.dist-info/top_level.txt
googletranslate_neon_plugin-0.1.1a0.dist-info/zip-safe
googletranslate_neon_plugin-0.1.1a0.dist-info/RECORD
